setup.py
similasdistributions/Binomialdistribution.py
similasdistributions/Gaussiandistribution.py
similasdistributions/Generaldistribution.py
similasdistributions/__init__.py
similasdistributions.egg-info/PKG-INFO
similasdistributions.egg-info/SOURCES.txt
similasdistributions.egg-info/dependency_links.txt
similasdistributions.egg-info/not-zip-safe
similasdistributions.egg-info/top_level.txt